git_additions/__helpers.py
git_additions/__init__.py
git_additions/duration/__init__.py
git_additions/duration/duration.py
git_additions/exporter/__init__.py
git_additions/exporter/csv_exporter.py
git_additions/logs/__init__.py
git_additions/logs/logs.py
git_additions/logs/print_log.py
git_additions/logs/t_colors.py
git_additions/stats/__init__.py
git_additions/stats/stats.py
git_additions/users/__init__.py
git_additions/users/users.py
git_additions-0.1.0.71.post0.dist-info/LICENSE
git_additions-0.1.0.71.post0.dist-info/METADATA
git_additions-0.1.0.71.post0.dist-info/WHEEL
git_additions-0.1.0.71.post0.dist-info/entry_points.txt
git_additions-0.1.0.71.post0.dist-info/top_level.txt
git_additions-0.1.0.71.post0.dist-info/RECORD
