Metadata-Version: 2.1
Name: git-additions
Version: 0.1.0.71.post0
Summary: Git additions.
Home-page: https://github.com/eendroroy/git-additions
Author: indrajit
Author-email: eendroroy@gmail.com
License: MIT
Platform: any
Classifier: Programming Language :: Python :: 2
Classifier: Programming Language :: Python :: 3
Classifier: License :: OSI Approved :: MIT License
Classifier: Development Status :: 4 - Beta
Classifier: Intended Audience :: End Users/Desktop
Requires-Dist: pygit2
Requires-Dist: colorama
